quickparse/__init__.py
quickparse/lib.py
quickparse/quickparse.py
quickparse-0.9.1.dist-info/LICENSE
quickparse-0.9.1.dist-info/WHEEL
quickparse-0.9.1.dist-info/METADATA
quickparse-0.9.1.dist-info/RECORD
