Metadata-Version: 2.1
Name: quickparse
Version: 0.9.1
Summary: Simple command line argument parser for Python
Home-page: https://github.com/silkyanteater/quickparse
License: MIT
Keywords: command line,argument,parser
Author: silkyanteater
Author-email: cyclopesrufus@gmail.com
Requires-Python: >=3.5,<4.0
Classifier: License :: OSI Approved :: MIT License
Classifier: Programming Language :: Python :: 3
Classifier: Programming Language :: Python :: 3.5
Classifier: Programming Language :: Python :: 3.6
Classifier: Programming Language :: Python :: 3.7
Classifier: Programming Language :: Python :: 3.8
Classifier: Programming Language :: Python :: 3.9
Project-URL: Repository, https://github.com/silkyanteater/quickparse
